tzcron.py
tzcron-1.0.0.dist-info/DESCRIPTION.rst
tzcron-1.0.0.dist-info/METADATA
tzcron-1.0.0.dist-info/RECORD
tzcron-1.0.0.dist-info/WHEEL
tzcron-1.0.0.dist-info/metadata.json
tzcron-1.0.0.dist-info/top_level.txt
